tmebot/__init__.py
tmebot/app.py
tmebot/bot.py
tmebot/logger.py
tmebot/polling.py
tmebot/filters/__init__.py
tmebot/filters/chat_type.py
tmebot/filters/text.py
tmebot-1.0.1.dist-info/METADATA
tmebot-1.0.1.dist-info/WHEEL
tmebot-1.0.1.dist-info/RECORD
